sslsv/Config.py
sslsv/__init__.py
sslsv/bin/__init__.py
sslsv/bin/evaluate.py
sslsv/bin/evaluate_label_efficient.py
sslsv/bin/profiling.py
sslsv/bin/train.py
sslsv/bin/train_distributed.py
sslsv/datasets/DataAugmentation.py
sslsv/datasets/Dataset.py
sslsv/datasets/DistributedSamplerWrapper.py
sslsv/datasets/SSLDataset.py
sslsv/datasets/Sampler.py
sslsv/datasets/__init__.py
sslsv/datasets/utils.py
sslsv/encoders/ECAPATDNN.py
sslsv/encoders/ResNet34.py
sslsv/encoders/SimpleAudioCNN.py
sslsv/encoders/TDNN.py
sslsv/encoders/_BaseEncoder.py
sslsv/encoders/__init__.py
sslsv/evaluations/ClassificationEvaluation.py
sslsv/evaluations/CosineSVEvaluation.py
sslsv/evaluations/PLDASVEvaluation.py
sslsv/evaluations/_BaseEvaluation.py
sslsv/evaluations/_SpeakerVerificationEvaluation.py
sslsv/evaluations/__init__.py
sslsv/methods/_BaseMethod.py
sslsv/methods/_BaseMomentumMethod.py
sslsv/methods/_BaseSiameseMethod.py
sslsv/methods/__init__.py
sslsv/methods/BYOL/BYOL.py
sslsv/methods/BYOL/BYOLLoss.py
sslsv/methods/BYOL/__init__.py
sslsv/methods/BarlowTwins/BarlowTwins.py
sslsv/methods/BarlowTwins/BarlowTwinsLoss.py
sslsv/methods/BarlowTwins/__init__.py
sslsv/methods/CPC/CPC.py
sslsv/methods/CPC/CPCLoss.py
sslsv/methods/CPC/InfoNCELoss.py
sslsv/methods/CPC/__init__.py
sslsv/methods/Combiner/Combiner.py
sslsv/methods/Combiner/__init__.py
sslsv/methods/DINO/DINO.py
sslsv/methods/DINO/DINOLoss.py
sslsv/methods/DINO/__init__.py
sslsv/methods/DeepCluster/DeepCluster.py
sslsv/methods/DeepCluster/DeepClusterLoss.py
sslsv/methods/DeepCluster/KMeans.py
sslsv/methods/DeepCluster/__init__.py
sslsv/methods/LIM/LIM.py
sslsv/methods/LIM/LIMLoss.py
sslsv/methods/LIM/__init__.py
sslsv/methods/MoCo/MoCo.py
sslsv/methods/MoCo/MoCoLoss.py
sslsv/methods/MoCo/__init__.py
sslsv/methods/SimCLR/SimCLR.py
sslsv/methods/SimCLR/SimCLRLoss.py
sslsv/methods/SimCLR/__init__.py
sslsv/methods/SimCLRCustom/SimCLRCustom.py
sslsv/methods/SimCLRCustom/SimCLRCustomLoss.py
sslsv/methods/SimCLRCustom/__init__.py
sslsv-0.0.1.dist-info/METADATA
sslsv-0.0.1.dist-info/WHEEL
sslsv-0.0.1.dist-info/licenses/LICENSE.md
sslsv-0.0.1.dist-info/RECORD
