Metadata-Version: 2.3
Name: sslsv
Version: 0.0.1
Summary: Framework for training and evaluating self-supervised learning methods for speaker verification.
Project-URL: Homepage, https://github.com/theolepage/sslsv
Project-URL: Issues, https://github.com/theolepage/sslsv/issues
Author-email: Theo Lepage <theo@theolepage.com>
License-File: LICENSE.md
Classifier: License :: OSI Approved :: MIT License
Classifier: Operating System :: OS Independent
Classifier: Programming Language :: Python :: 3
Requires-Python: >=3.8
